Metadata-Version: 2.1
Name: mscheck
Version: 0.3.1b0
Summary: Auto MS mass checker
Home-page: https://github.com/Waztom/mscheck
Author: Warren Thompson
Author-email: waztom@gmail.com
License: MIT
Platform: UNKNOWN
Classifier: Intended Audience :: Developers
Classifier: Intended Audience :: Science/Research
Classifier: License :: OSI Approved :: MIT License
Classifier: Programming Language :: Python :: 3.7
Classifier: Topic :: Software Development :: Libraries :: Python Modules
